mcpl_core-2.2.6.dist-info/RECORD
mcpl_core-2.2.6.dist-info/WHEEL
mcpl_core-2.2.6.dist-info/entry_points.txt
mcpl_core-2.2.6.dist-info/METADATA
mcpl_core-2.2.6.dist-info/licenses/LICENSE
_mcpl_core/__init__.py
_mcpl_core/info.py
_mcpl_core/data/bin/mcpltool
_mcpl_core/data/bin/mcpl-config
_mcpl_core/data/include/mcpl.h
_mcpl_core/data/lib/libmcpl.dylib
_mcpl_core/data/lib/cmake/MCPL/MCPLConfigVersion.cmake
_mcpl_core/data/lib/cmake/MCPL/MCPLTargets-release.cmake
_mcpl_core/data/lib/cmake/MCPL/MCPLTargets.cmake
_mcpl_core/data/lib/cmake/MCPL/MCPLConfig.cmake
