Metadata-Version: 2.2
Name: mcpl-core
Version: 2.2.6
Summary: Utilities and API for accessing MCPL (.mcpl) files
Author: MCPL developers (Thomas Kittelmann, et. al.)
License: Apache-2.0
Classifier: Programming Language :: Python :: 3
Classifier: License :: OSI Approved :: Apache Software License
Project-URL: Homepage, https://mctools.github.io/mcpl/
Project-URL: Bug Tracker, https://github.com/mctools/mcpl/issues
Requires-Python: >=3.8
